torch_similarity_search/__init__.py
torch_similarity_search/converters/__init__.py
torch_similarity_search/converters/faiss_converter.py
torch_similarity_search/indexes/__init__.py
torch_similarity_search/indexes/base.py
torch_similarity_search/indexes/flat.py
torch_similarity_search/indexes/ivf_flat.py
torch_similarity_search/indexes/ivf_pq.py
torch_similarity_search/utils/__init__.py
torch_similarity_search/utils/distance.py
torch_similarity_search-0.0.4.dist-info/METADATA
torch_similarity_search-0.0.4.dist-info/WHEEL
torch_similarity_search-0.0.4.dist-info/RECORD
