Metadata-Version: 2.4
Name: torch-similarity-search
Version: 0.0.4
Summary: PyTorch-native similarity search: convert FAISS indexes to nn.Module
Requires-Python: >=3.11
Requires-Dist: numpy>=1.20
Requires-Dist: torch>=2.0
